LICENSE
README.md
VERSION
pyproject.toml
ocp_utilities/__init__.py
ocp_utilities/debugger.py
ocp_utilities/exceptions.py
ocp_utilities/infra.py
ocp_utilities/monitoring.py
ocp_utilities/must_gather.py
ocp_utilities/operators.py
ocp_utilities/utils.py
openshift_python_utilities.egg-info/PKG-INFO
openshift_python_utilities.egg-info/SOURCES.txt
openshift_python_utilities.egg-info/dependency_links.txt
openshift_python_utilities.egg-info/requires.txt
openshift_python_utilities.egg-info/top_level.txt