Metadata-Version: 2.1
Name: openshift-python-utilities
Version: 4.13.17
Summary: A utilities repository for https://github.com/RedHatQE/openshift-python-wrapper
Author-email: Meni Yakove <myakove@gmail.com>, Ruth Netser <rnetser@gmail.com>
Project-URL: Homepage, https://github.com/RedHatQE/openshift-python-utilities
Project-URL: Download, https://pypi.org/project/openshift-python-utilities/
Project-URL: Bug Tracker, https://github.com/RedHatQE/openshift-python-utilities/issues
Project-URL: Documentation, https://github.com/RedHatQE/openshift-python-utilities/blob/main/README.md
Keywords: Openshift
Classifier: Programming Language :: Python :: 3
Classifier: Operating System :: OS Independent
Requires-Python: >=3.8
License-File: LICENSE
